Metadata-Version: 2.1
Name: awesome-messages
Version: 1.0.0
Summary: This module provides interfaces to work with any kind of message publisher and consumer like rabbitmq pubsub.
Home-page: https://github.com/elchicodepython/python_awesome_messages
Author: Samuel López Saura
Author-email: samuellopezsaura@gmail.com
License: MIT
Platform: UNKNOWN
Classifier: Programming Language :: Python :: 3
Classifier: License :: OSI Approved :: MIT License
Classifier: Operating System :: OS Independent
License-File: LICENSE
